
[{"content":" Quality Assurance # ","date":"23 May 2024","externalUrl":null,"permalink":"/qualityassurance/","section":"","summary":" Quality Assurance # ","title":"","type":"qualityassurance"},{"content":"","date":"23 May 2024","externalUrl":null,"permalink":"/categories/","section":"Categories","summary":"","title":"Categories","type":"categories"},{"content":"","date":"23 May 2024","externalUrl":null,"permalink":"/tags/congo/","section":"Tags","summary":"","title":"Congo","type":"tags"},{"content":"","date":"23 May 2024","externalUrl":null,"permalink":"/categories/development/","section":"Categories","summary":"","title":"Development","type":"categories"},{"content":"","date":"23 May 2024","externalUrl":null,"permalink":"/tags/docker/","section":"Tags","summary":"","title":"Docker","type":"tags"},{"content":"","date":"23 May 2024","externalUrl":null,"permalink":"/tags/hugo/","section":"Tags","summary":"","title":"Hugo","type":"tags"},{"content":"","date":"23 May 2024","externalUrl":null,"permalink":"/","section":"NCW","summary":"","title":"NCW","type":"page"},{"content":"","date":"23 May 2024","externalUrl":null,"permalink":"/tags/","section":"Tags","summary":"","title":"Tags","type":"tags"},{"content":"","date":"23 May 2024","externalUrl":null,"permalink":"/categories/test/","section":"Categories","summary":"","title":"Test","type":"categories"},{"content":"\u0026ldquo;Sed ut perspiciatis unde omnis iste natus error sit voluptatem accusantium doloremque laudantium, totam rem aperiam, eaque ipsa quae ab illo inventore veritatis et quasi architecto beatae vitae dicta sunt explicabo. Nemo enim ipsam voluptatem quia voluptas sit aspernatur aut odit aut fugit, sed quia consequuntur magni dolores eos qui ratione voluptatem sequi nesciunt. Neque porro quisquam est, qui dolorem ipsum quia dolor sit amet, consectetur, adipisci velit, sed quia non numquam eius modi tempora incidunt ut labore et dolore magnam aliquam quaerat voluptatem. Ut enim ad minima veniam, quis nostrum exercitationem ullam corporis suscipit laboriosam, nisi ut aliquid ex ea commodi consequatur? Quis autem vel eum iure reprehenderit qui in ea voluptate velit esse quam nihil molestiae consequatur, vel illum qui dolorem eum fugiat quo voluptas nulla pariatur?\u0026rdquo;\n","date":"23 May 2024","externalUrl":null,"permalink":"/qualityassurance/20240523-test-article/","section":"","summary":"\u0026ldquo;Sed ut perspiciatis unde omnis iste natus error sit voluptatem accusantium doloremque laudantium, totam rem aperiam, eaque ipsa quae ab illo inventore veritatis et quasi architecto beatae vitae dicta sunt explicabo.","title":"This is my first test article","type":"qualityassurance"},{"content":"","date":"23 May 2024","externalUrl":null,"permalink":"/tags/vscode/","section":"Tags","summary":"","title":"VSCode","type":"tags"},{"content":"","date":"1 January 0001","externalUrl":null,"permalink":"/about/","section":"NCW","summary":"","title":"","type":"page"},{"content":"","date":"1 January 0001","externalUrl":null,"permalink":"/authors/","section":"Authors","summary":"","title":"Authors","type":"authors"},{"content":"","date":"1 January 0001","externalUrl":null,"permalink":"/series/","section":"Series","summary":"","title":"Series","type":"series"}]